Metadata-Version: 1.0
Name: Gaussian-Binomial-dist-SL
Version: 1.0
Summary: Gaussian and Binomial distributions
Home-page: UNKNOWN
Author: Sikang Luan
Author-email: micluan41@gmail.com
License: UNKNOWN
Platform: UNKNOWN
